tldextract/.tld_set_snapshot
tldextract/__init__.py
tldextract/__main__.py
tldextract/_version.py
tldextract/cache.py
tldextract/cli.py
tldextract/py.typed
tldextract/remote.py
tldextract/suffix_list.py
tldextract/tldextract.py
tldextract-5.1.0.dist-info/LICENSE
tldextract-5.1.0.dist-info/METADATA
tldextract-5.1.0.dist-info/WHEEL
tldextract-5.1.0.dist-info/entry_points.txt
tldextract-5.1.0.dist-info/top_level.txt
tldextract-5.1.0.dist-info/RECORD
