Metadata-Version: 2.1
Name: tldextract
Version: 5.1.0
Summary: Accurately separates a URL's subdomain, domain, and public suffix, using the Public Suffix List (PSL). By default, this includes the public ICANN TLDs and their exceptions. You can optionally support the Public Suffix List's private domains as well.
Author-email: John Kurkowski <john.kurkowski@gmail.com>
License: BSD-3-Clause
Project-URL: Homepage, https://github.com/john-kurkowski/tldextract
Keywords: tld,domain,subdomain,url,parse,extract,urlparse,urlsplit,public,suffix,list,publicsuffix,publicsuffixlist
Classifier: Development Status :: 5 - Production/Stable
Classifier: Topic :: Utilities
Classifier: License :: OSI Approved :: BSD License
Classifier: Programming Language :: Python :: 3
Classifier: Programming Language :: Python :: 3.8
Classifier: Programming Language :: Python :: 3.9
Classifier: Programming Language :: Python :: 3.10
Classifier: Programming Language :: Python :: 3.11
Requires-Python: >=3.8
License-File: LICENSE
Requires-Dist: idna
Requires-Dist: requests>=2.1.0
Requires-Dist: requests-file>=1.4
Requires-Dist: filelock>=3.0.8
Provides-Extra: testing
Requires-Dist: black; extra == "testing"
Requires-Dist: mypy; extra == "testing"
Requires-Dist: pytest; extra == "testing"
Requires-Dist: pytest-gitignore; extra == "testing"
Requires-Dist: pytest-mock; extra == "testing"
Requires-Dist: responses; extra == "testing"
Requires-Dist: ruff; extra == "testing"
Requires-Dist: tox; extra == "testing"
Requires-Dist: types-filelock; extra == "testing"
Requires-Dist: types-requests; extra == "testing"
